starfish/__init__.py
starfish/constants.py
starfish/exceptions.py
starfish/types.py
starfish/agent/__init__.py
starfish/agent/agent_base.py
starfish/agent/memory_agent.py
starfish/agent/remote_agent.py
starfish/agent/authentication/__init__.py
starfish/agent/authentication/authentication.py
starfish/agent/authentication/authentication_basic.py
starfish/agent/authentication/authentication_token.py
starfish/agent_manager/__init__.py
starfish/agent_manager/agent_access.py
starfish/agent_manager/agent_manager.py
starfish/asset/__init__.py
starfish/asset/asset_base.py
starfish/asset/bundle_asset.py
starfish/asset/data_asset.py
starfish/asset/operation_asset.py
starfish/asset/provenance.py
starfish/asset/remote_data_asset.py
starfish/job/__init__.py
starfish/job/job.py
starfish/listing/__init__.py
starfish/listing/listing.py
starfish/listing/listing_base.py
starfish/metadata_old/__init__.py
starfish/metadata_old/metadata.py
starfish/middleware/__init__.py
starfish/middleware/agent/__init__.py
starfish/middleware/agent/remote_agent_adapter.py
starfish/network/__init__.py
starfish/network/account_base.py
starfish/network/ddo.py
starfish/network/did.py
starfish/network/network_base.py
starfish/network/convex/__init__.py
starfish/network/convex/convex_account.py
starfish/network/convex/convex_keypair.py
starfish/network/convex/convex_network.py
starfish/network/convex/contract/__init__.py
starfish/network/convex/contract/contract_manager.py
starfish/network/convex/contract/did_contract.py
starfish/network/convex/contract/provenance_contract.py
starfish/purchase/__init__.py
starfish/purchase/purchase.py
starfish/purchase/purchase_base.py
starfish/tool/__init__.py
starfish/tool/output.py
starfish/tool/command/__init__.py
starfish/tool/command/account_balance_command.py
starfish/tool/command/account_command.py
starfish/tool/command/account_create_command.py
starfish/tool/command/account_get_command.py
starfish/tool/command/account_get_token_command.py
starfish_py-0.17.16.dist-info/LICENSE
starfish_py-0.17.16.dist-info/METADATA
starfish_py-0.17.16.dist-info/WHEEL
starfish_py-0.17.16.dist-info/top_level.txt
starfish_py-0.17.16.dist-info/RECORD
